JsonCrack/AutoSchema.py
JsonCrack/Cracker.py
JsonCrack/__init__.py
JsonCrack/fuctions.py
jsoncrack-0.2.1.dist-info/METADATA
jsoncrack-0.2.1.dist-info/WHEEL
jsoncrack-0.2.1.dist-info/top_level.txt
jsoncrack-0.2.1.dist-info/RECORD
