Metadata-Version: 2.2
Name: JsonCrack
Version: 0.2.1
Summary: A Python package to visualize JSON as a vertical graph(support drf-spectacular).
Author-email: Mahmoud Gamal <mahmoudgshaker2018@gmail.com>
License: MIT
Project-URL: Repository, https://github.com/MahmoudGShake/JsonCrack.git
Requires-Dist: graphviz
Requires-Dist: drf-spectacular
